aiohttp_oauth2/__init__.py
aiohttp_oauth2/client/__init__.py
aiohttp_oauth2/client/app.py
aiohttp_oauth2/client/contrib.py
aiohttp_oauth2/client/views.py
aiohttp_oauth2-0.0.5.dist-info/LICENSE.txt
aiohttp_oauth2-0.0.5.dist-info/METADATA
aiohttp_oauth2-0.0.5.dist-info/WHEEL
aiohttp_oauth2-0.0.5.dist-info/top_level.txt
aiohttp_oauth2-0.0.5.dist-info/RECORD
