Metadata-Version: 2.1
Name: aiohttp-oauth2
Version: 0.0.5
Summary: Provider agnostic OAuth2 client for aiohttp
Home-page: https://github.com/mrasband/aiohttp-oauth2
Author: Matt Rasband
Author-email: matt.rasband@gmail.com
License: UNKNOWN
Keywords: aiohttp,oauth2
Platform: UNKNOWN
Classifier: Programming Language :: Python
Classifier: Programming Language :: Python :: 3
Classifier: Programming Language :: Python :: 3.7
Classifier: Programming Language :: Python :: 3.8
Classifier: Programming Language :: Python :: Implementation :: CPython
Requires-Python: >=3.7.0
Requires-Dist: aiohttp
